financial_reports_generated_client/__init__.py
financial_reports_generated_client/api_client.py
financial_reports_generated_client/api_response.py
financial_reports_generated_client/client.py
financial_reports_generated_client/configuration.py
financial_reports_generated_client/exceptions.py
financial_reports_generated_client/py.typed
financial_reports_generated_client/rest.py
financial_reports_generated_client/api/__init__.py
financial_reports_generated_client/api/companies_api.py
financial_reports_generated_client/api/countries_api.py
financial_reports_generated_client/api/default_api.py
financial_reports_generated_client/api/filing_categories_api.py
financial_reports_generated_client/api/filing_types_api.py
financial_reports_generated_client/api/filings_api.py
financial_reports_generated_client/api/isic_classifications_api.py
financial_reports_generated_client/api/languages_api.py
financial_reports_generated_client/api/sources_api.py
financial_reports_generated_client/api/watchlist_api.py
financial_reports_generated_client/api/webhooks_management_api.py
financial_reports_generated_client/models/__init__.py
financial_reports_generated_client/models/company.py
financial_reports_generated_client/models/company_minimal.py
financial_reports_generated_client/models/country.py
financial_reports_generated_client/models/designated_sponsor.py
financial_reports_generated_client/models/error_detail.py
financial_reports_generated_client/models/filing.py
financial_reports_generated_client/models/filing_category.py
financial_reports_generated_client/models/filing_processed_payload.py
financial_reports_generated_client/models/filing_summary.py
financial_reports_generated_client/models/filing_type.py
financial_reports_generated_client/models/isic_class.py
financial_reports_generated_client/models/isic_division.py
financial_reports_generated_client/models/isic_group.py
financial_reports_generated_client/models/isic_section.py
financial_reports_generated_client/models/language.py
financial_reports_generated_client-1.4.2.dist-info/METADATA
financial_reports_generated_client-1.4.2.dist-info/WHEEL
financial_reports_generated_client-1.4.2.dist-info/top_level.txt
financial_reports_generated_client-1.4.2.dist-info/RECORD
