Metadata-Version: 2.4
Name: financial_reports_generated_client
Version: 1.4.2
Summary: FinancialReports API
Home-page: 
Author: API Support
Author-email: API Support <api@financialreports.eu>
License: Apache-2.0
Project-URL: Repository, https://github.com/GIT_USER_ID/GIT_REPO_ID
Keywords: OpenAPI,OpenAPI-Generator,FinancialReports API
Requires-Python: >=3.9
Requires-Dist: python-dateutil>=2.8.2
Requires-Dist: aiohttp>=3.8.4
Requires-Dist: aiohttp-retry>=2.8.3
Requires-Dist: pydantic>=2
Requires-Dist: typing-extensions>=4.7.1
Dynamic: author
